hooks/copy_source_markdown.py
scripts/benchmark_lazy.py
scripts/cov_summary.py
scripts/gen_changelog.py
scripts/gen_ref_pages.py
scripts/generate_rendering_docs.py
scripts/get_changed_docs_urls.py
scripts/reorder_versions.py
sleap_io/__init__.py
sleap_io/version.py
sleap_io/codecs/__init__.py
sleap_io/codecs/dataframe.py
sleap_io/codecs/dictionary.py
sleap_io/codecs/numpy.py
sleap_io/io/__init__.py
sleap_io/io/alphatracker.py
sleap_io/io/analysis_h5.py
sleap_io/io/cli.py
sleap_io/io/coco.py
sleap_io/io/csv.py
sleap_io/io/dlc.py
sleap_io/io/jabs.py
sleap_io/io/labelstudio.py
sleap_io/io/leap.py
sleap_io/io/main.py
sleap_io/io/nwb.py
sleap_io/io/nwb_annotations.py
sleap_io/io/nwb_predictions.py
sleap_io/io/skeleton.py
sleap_io/io/slp.py
sleap_io/io/slp_lazy.py
sleap_io/io/ultralytics.py
sleap_io/io/utils.py
sleap_io/io/video_reading.py
sleap_io/io/video_writing.py
sleap_io/model/__init__.py
sleap_io/model/camera.py
sleap_io/model/instance.py
sleap_io/model/labeled_frame.py
sleap_io/model/labels.py
sleap_io/model/labels_set.py
sleap_io/model/matching.py
sleap_io/model/skeleton.py
sleap_io/model/suggestions.py
sleap_io/model/video.py
sleap_io/rendering/__init__.py
sleap_io/rendering/callbacks.py
sleap_io/rendering/colors.py
sleap_io/rendering/core.py
sleap_io/rendering/shapes.py
sleap_io/transform/__init__.py
sleap_io/transform/core.py
sleap_io/transform/frame.py
sleap_io/transform/points.py
sleap_io/transform/video.py
sleap_io-0.6.3.dist-info/licenses/LICENSE
tests/__init__.py
tests/conftest.py
tests/codecs/__init__.py
tests/codecs/test_dataframe.py
tests/codecs/test_dictionary.py
tests/codecs/test_numpy.py
tests/fixtures/alphatracker.py
tests/fixtures/camera.py
tests/fixtures/coco.py
tests/fixtures/cvat.py
tests/fixtures/dlc.py
tests/fixtures/jabs.py
tests/fixtures/labels.py
tests/fixtures/labelstudio.py
tests/fixtures/leap.py
tests/fixtures/merge_fixtures.py
tests/fixtures/slp.py
tests/fixtures/ultralytics.py
tests/fixtures/videos.py
tests/io/test_alphatracker.py
tests/io/test_analysis_h5.py
sleap_io-0.6.3.dist-info/METADATA
sleap_io-0.6.3.dist-info/WHEEL
sleap_io-0.6.3.dist-info/entry_points.txt
sleap_io-0.6.3.dist-info/top_level.txt
sleap_io-0.6.3.dist-info/RECORD
