Metadata-Version: 2.4
Name: sleap-io
Version: 0.6.3
Summary: Standalone utilities for working with pose data from SLEAP and other tools.
Author-email: Divya Murali <divya@talmolab.org>, Liezl Maree <lmaree@salk.edu>, David Samy <davidasamy@gmail.com>, Talmo Pereira <talmo@salk.edu>
License: BSD-3-Clause
Project-URL: Homepage, https://io.sleap.ai
Project-URL: Repository, https://github.com/talmolab/sleap-io
Keywords: sleap,pose tracking,pose estimation,behavior
Classifier: Programming Language :: Python :: 3.10
Classifier: Programming Language :: Python :: 3.11
Classifier: Programming Language :: Python :: 3.12
Classifier: Programming Language :: Python :: 3.13
Requires-Python: >=3.10
License-File: LICENSE
Requires-Dist: numpy
Requires-Dist: attrs
Requires-Dist: h5py>=3.8.0
Requires-Dist: pynwb
Requires-Dist: ndx-pose>=0.2.1
Requires-Dist: ndx-multisubjects>=0.1.1
Requires-Dist: pandas
Requires-Dist: simplejson
Requires-Dist: imageio
Requires-Dist: imageio-ffmpeg>=0.5.0
Requires-Dist: tifffile
Requires-Dist: tqdm
Requires-Dist: pyyaml
Requires-Dist: rich_click
Requires-Dist: lazy-loader>=0.4
Requires-Dist: skia-python>=87.0
Requires-Dist: colorcet>=3.0
Provides-Extra: opencv
Requires-Dist: opencv-python; extra == "opencv"
Provides-Extra: pyav
Requires-Dist: av<16.0.0; extra == "pyav"
Provides-Extra: mat
Requires-Dist: pymatreader; extra == "mat"
Provides-Extra: polars
Requires-Dist: polars; extra == "polars"
Requires-Dist: pyarrow; extra == "polars"
Provides-Extra: all
Requires-Dist: opencv-python; extra == "all"
Requires-Dist: av<16.0.0; extra == "all"
Requires-Dist: pymatreader; extra == "all"
Requires-Dist: polars; extra == "all"
Requires-Dist: pyarrow; extra == "all"
Dynamic: license-file
